pyellipsoid/__init__.py
pyellipsoid/analysis.py
pyellipsoid/drawing.py
pyellipsoid/geometry.py
pyellipsoid-0.0.3.dist-info/LICENSE.txt
pyellipsoid-0.0.3.dist-info/METADATA
pyellipsoid-0.0.3.dist-info/WHEEL
pyellipsoid-0.0.3.dist-info/top_level.txt
pyellipsoid-0.0.3.dist-info/RECORD
