Metadata-Version: 2.1
Name: pyellipsoid
Version: 0.0.3
Summary: Ellipsoids drawing and analysis in 3D volumetric images.
Home-page: https://github.com/ashkarin/pyellipsoid
Author: Andrei Shkarin
Author-email: andrei.shkarin@gmail.com
License: UNKNOWN
Project-URL: Bug Reports, https://github.com/ashkarin/pyellipsoid/issues
Project-URL: Source, https://github.com/ashkarin/pyellipsoid
Keywords: ellipsoid drawing rotation analysis
Platform: UNKNOWN
Classifier: Development Status :: 3 - Alpha
Classifier: Intended Audience :: Developers
Classifier: Intended Audience :: Science/Research
Classifier: License :: OSI Approved :: MIT License
Classifier: Topic :: Software Development :: Libraries :: Python Modules
Requires-Dist: numpy
